[
    {
      "url": "1.jpg",
      "title": "Плов",
      "description": "Восточное блюдо из риса, мяса и овощей.",
      "products": [
        "1 кг риса",
        "500 г мяса (говядины, баранины или курицы)",
        "2 луковицы",
        "2 моркови",
        "1 банка томатной пасты",
        "1 столовая ложка растительного масла",
        "1 чайная ложка соли",
        "1/2 чайной ложки черного перца",
        "1/4 чайной ложки куркумы",
        "1/4 чайной ложки зирна",
        "1/4 чайной ложки барбариса"
      ],
      "recept": [
        "1. Рис промойте несколько раз холодной водой, пока вода не станет прозрачной.",
        "2. Мясо нарежьте небольшими кусочками.",
        "3. Лук и морковь очистите и нарежьте соломкой.",
        "4. В кастрюле нагрейте растительное масло.",
        "5. Добавьте в кастрюлю мясо и обжарьте его до золотистого цвета.",
        "6. Добавьте в кастрюлю лук и морковь и жарьте еще 5 минут.",
        "7. Добавьте в кастрюлю рис и томатную пасту.",
        "8. Залейте рис водой в соотношении 1:2.",
        "9. Добавьте в рис соль, перец, куркуму, зирнэ и барбарис.",
        "10. Доведите рис до кипения, затем уменьшите огонь и варите на медленном огне 20 минут.",
        "11. Плов готов! Подавайте горячим со сметаной и зеленью."
        ]
      },
      {
      "url": "2.jpg",
      "title": "Бефстроганов",
      "description": "Блюдо из говядины, сметаны и лука.",
      "products": [
        "500 г говядины",
        "1 луковица",
        "1 столовая ложка муки",
        "1/2 стакана сметаны",
        "1 столовая ложка растительного масла",
        "1 чайная ложка соли",
        "1/2 чайной ложки черного перца"
      ],
      "recept": [
        "1. Говядину нарежьте тонкими ломтиками.",
        "2. Лук очистите и нарежьте соломкой.",
        "3. В кастрюле нагрейте растительное масло.",
        "4. Добавьте в кастрюлю говядину и обжарьте ее до золотистого цвета.",
        "5. Добавьте в кастрюлю лук и жарьте еще 5 минут.",
        "6. Добавьте в кастрюлю муку и перемешайте.",
        "7. Влейте в кастрюлю сметану, воду и доведите до кипения.",
        "8. Добавьте в кастрюлю соль, перец и варите еще 10 минут.",
        "9. Бефстроганов готов! Подавайте горячим с макаронами или картофельным пюре."
        ]
      },
      {
      "url": "3.jpg",
      "title": "Картофельное пюре",
      "description": "Блюдо из картофеля, молока и сливочного масла.",
      "products": [
        "1 кг картофеля",
        "500 мл молока",
        "100 г сливочного масла",
        "1 чайная ложка соли",
        "1/2 чайной ложки черного перца"
      ],
      "recept": [
        "1. Картофель очистите и отварите в кипящей воде до готовности.",
        "2. Слейте воду с картофеля и разомните его в пюре.",
        "3. В пюре добавьте молоко, сливочное масло, соль и перец.",
        "4. Хорошо перемешайте пюре до однородной массы.",
        "5. Картофельное пюре готово! Подавайте горячим с котлетами, рыбой или курицей."
        ]
      },
      {
        "url": "4.jpg",
        "title": "Шницель",
        "description": "Блюдо из свинины или говядины, обжаренной в панировке.",
        "products": [
          "500 г свинины или говядины",
          "1 яйцо",
          "1/2 стакана панировочных сухарей",
          "1 столовая ложка растительного масла",
          "1 чайная ложка соли",
          "1/2 чайной ложки черного перца"
        ],
        "recept": [
          "1. Мясо нарежьте тонкими ломтиками.",
          "2. В миске взбейте яйцо.",
          "3. В другой миске смешайте панировочные сухари, соль и перец.",
          "4. Каждый ломтик мяса обмакните в яйцо, а затем в панировочные сухари.",
          "5. В сковороде нагрейте растительное масло.",
          "6. Обжарьте шницель с обеих сторон до золотистого цвета.",
          "7. Шницель готов! Подавайте горячим с гарниром."
        ]
      },
      {
        "url": "5.jpg",
        "title": "Отбивная",
        "description": "Блюдо из свинины или говядины, отбивной.",
        "products": [
          "500 г свинины или говядины",
          "1 столовая ложка растительного масла",
          "1 чайная ложка соли",
          "1/2 чайной ложки черного перца"
        ],
        "recept": [
          "1. Мясо нарежьте тонкими ломтиками.",
          "2. В миске смешайте соль, перец и растительное масло.",
          "3. Каждый ломтик мяса обмакните в смесь.",
          "4. На сковороде нагрейте растительное масло.",
          "5. Обжарьте отбивную с обеих сторон до золотистого цвета.",
          "6. Отбивная готова! Подавайте горячим с гарниром."
        ]
      }
]     